structure_generator/__init__.py
structure_generator/_4D/__init__.py
structure_generator/_4D/generate_comp.py
structure_generator/_5D/__init__.py
structure_generator/_5D/generate_eta.py
structure_generator/basic/__init__.py
structure_generator/basic/distribution_generator.py
structure_generator/basic/utils.py
structure_generator/basic/write_matrix.py
structure_generator/scripts/__init__.py
structure_generator/scripts/generate_structure.py
structure_generator-0.0.3.dist-info/LICENSE
structure_generator-0.0.3.dist-info/METADATA
structure_generator-0.0.3.dist-info/WHEEL
structure_generator-0.0.3.dist-info/entry_points.txt
structure_generator-0.0.3.dist-info/top_level.txt
structure_generator-0.0.3.dist-info/RECORD
