Metadata-Version: 2.1
Name: structure_generator
Version: 0.0.3
Summary: This is a tool to generate eta and comp structure data.
Author-email: Wen Tan <2634918190@qq.com>
Project-URL: Homepage, https://github.com/sijintech/stk.git
Project-URL: Issues, https://github.com/sijintech/stk/issues/
Classifier: Programming Language :: Python :: 3
Classifier: License :: OSI Approved :: MIT License
Classifier: Operating System :: POSIX :: Linux
Requires-Python: >=3.8
License-File: LICENSE
Requires-Dist: numpy >=1.20.0
Requires-Dist: toml >=0.8.2
